ddddocr/__init__.py
ddddocr/common.onnx
ddddocr/common_det.onnx
ddddocr/common_old.onnx
ddddocrfix-1.5.5.dist-info/licenses/LICENSE
ddddocrfix-1.5.5.dist-info/METADATA
ddddocrfix-1.5.5.dist-info/WHEEL
ddddocrfix-1.5.5.dist-info/top_level.txt
ddddocrfix-1.5.5.dist-info/RECORD
